AUTHORS
LICENSE
README.md
setup.py
mnqueues/__init__.py
mnqueues/gcp_monitor.py
mnqueues/log_monitor.py
mnqueues.egg-info/PKG-INFO
mnqueues.egg-info/SOURCES.txt
mnqueues.egg-info/dependency_links.txt
mnqueues.egg-info/requires.txt
mnqueues.egg-info/top_level.txt
requirements/release.txt