Metadata-Version: 2.1
Name: mnqueues
Version: 0.0.31
Summary: Monitored Multiprocessing Queues in Python
Home-page: https://github.com/amor71/mnqueues
Author: amor71
Author-email: amor71@sgeltd.com
License: MIT
Platform: UNKNOWN
Classifier: Programming Language :: Python :: 3.9
Classifier: License :: OSI Approved :: MIT License
Classifier: Operating System :: OS Independent
Requires-Python: >=3.9
License-File: LICENSE
License-File: AUTHORS
